{"agent-data-plane_index.md":"Xk_1ibJl","agent-data-plane_releasing.md":"N4-XdmIN","api-docs_index.md":"DphWOiEt","development_common-language.md":"QfNm8xW7","development_contributing.md":"DTjJsLJ3","development_index.md":"DVkjLm-0","development_style-guide.md":"DZ7-Vm2Y","development_testing.md":"DTMbRfHw","index.md":"JJhCvN53","reference_adrs__template.md":"DOPUWgJT","reference_adrs_index.md":"BnIFbdUW","reference_adrs_records_001-open-design-docs.md":"CQsRHBrX","reference_architecture_index.md":"DYPVeEAR","reference_proposals_index.md":"Jyq8xsi_"}
