{"agent-data-plane_configuration_dogstatsd.md":"CzIpYNUf","agent-data-plane_index.md":"DlnPv833","agent-data-plane_releasing.md":"DLbvBLTE","api-docs_index.md":"BWNQB3hy","development_common-language.md":"CspNZ_ft","development_contributing.md":"DYZwID5_","development_index.md":"BBNSL3YA","development_style-guide.md":"zu-xGQtx","development_testing.md":"BPzyezSV","index.md":"DK0V42bY","reference_adrs__template.md":"DQa6pHsa","reference_adrs_index.md":"CHJVA5ZU","reference_adrs_records_001-open-design-docs.md":"KBC3w0Wo","reference_architecture_index.md":"DzUKdROx","reference_proposals_index.md":"d42HzqeH"}
