{"agent-data-plane_configuration_dogstatsd.md":"DdvET4OH","agent-data-plane_index.md":"p6yQFL8-","agent-data-plane_memory.md":"C8-3AWq4","agent-data-plane_releasing.md":"BOEOxoFy","api-docs_index.md":"Cx2g4Sxc","development_common-language.md":"Bb6U3IBb","development_contributing.md":"BREiqjrJ","development_index.md":"Dw3RUHE_","development_style-guide.md":"C71MXcuY","development_testing.md":"BjcbJQr_","index.md":"DujpurYg","reference_adrs__template.md":"BNSWjrzp","reference_adrs_index.md":"CSfGGcni","reference_adrs_records_001-open-design-docs.md":"DaRuNhOJ","reference_architecture_index.md":"B0beuyZS","reference_proposals_index.md":"CdbUnH9Z"}
