{"agent-data-plane_configuration_dogstatsd.md":"BIR3L-i1","agent-data-plane_index.md":"NypZnkVc","agent-data-plane_releasing.md":"r1rZ_v_8","api-docs_index.md":"CLzYnwma","development_common-language.md":"Bbot9EFU","development_contributing.md":"B62i87kT","development_index.md":"B-HO191Q","development_style-guide.md":"BtYNcq69","development_testing.md":"Cpvcm8bK","index.md":"CgHiaZ6y","reference_adrs__template.md":"B_nEZh0r","reference_adrs_index.md":"D6XF-EIn","reference_adrs_records_001-open-design-docs.md":"BZx6EFnh","reference_architecture_index.md":"CokXvjMI","reference_proposals_index.md":"USJJnZUU"}
